MANIFEST.in
README.txt
setup.py
mysql_replay/__init__.py
mysql_replay/execute.py
mysql_replay/prepare.py
mysql_replay.egg-info/PKG-INFO
mysql_replay.egg-info/SOURCES.txt
mysql_replay.egg-info/dependency_links.txt
mysql_replay.egg-info/entry_points.txt
mysql_replay.egg-info/requires.txt
mysql_replay.egg-info/top_level.txt
mysql_replay/mysql/__init__.py
mysql_replay/mysql/utilities/__init__.py
mysql_replay/mysql/utilities/exception.py
mysql_replay/mysql/utilities/common/__init__.py
mysql_replay/mysql/utilities/common/parser.py