Metadata-Version: 1.0
Name: mysql-replay
Version: 0.1.23
Summary: Replay queries from a mysql slow log
Home-page: https://pypi.python.org/pypi/mysql-replay
Author: Hugo Chinchilla
Author-email: hchinchilla@habitissimo.com
License: GPLv3
Keywords: mysql bechmarking log slow
Platform: UNKNOWN
